[
  {
    "name": "IDFLY Labs",
    "positions": [
      "[06.2014 - н.в] - Руководитель отдела разработки",
      "[04.2014 - 05.2016] - Ведуший программист"
    ]
  },
  {
    "name": "Пензенский государтвенный университет",
    "positions": [
      "[10.2011 - 04.2015] - Программист"
    ]
  },
  {
    "name": "Фрилансер",
    "positions": [
      "[05.2012 - 04.2014] - Фрилансер"
    ]
  },
  {
    "name": "ОАО \"НПП \"Рубин\"",
    "positions": [
      "[06.2010 - 02.2012] - Инженер-программист"
    ]
  }
]